dataiter/__init__.py
dataiter/aggregate.py
dataiter/data_frame.py
dataiter/deco.py
dataiter/dt.py
dataiter/dtypes.py
dataiter/geojson.py
dataiter/io.py
dataiter/list_of_dicts.py
dataiter/regex.py
dataiter/util.py
dataiter/vector.py
dataiter/test/__init__.py
dataiter/test/test_aggregate.py
dataiter/test/test_data_frame.py
dataiter/test/test_dt.py
dataiter/test/test_geojson.py
dataiter/test/test_io.py
dataiter/test/test_list_of_dicts.py
dataiter/test/test_regex.py
dataiter/test/test_util.py
dataiter/test/test_vector.py
dataiter-1.1.dist-info/METADATA
dataiter-1.1.dist-info/WHEEL
dataiter-1.1.dist-info/licenses/AUTHORS.md
dataiter-1.1.dist-info/licenses/COPYING
dataiter-1.1.dist-info/RECORD
