Metadata-Version: 2.1
Name: dataiter
Version: 1.1
Summary: Simple, light-weight data frames for Python
Project-URL: Homepage, https://github.com/otsaloma/dataiter
Author-email: Osmo Salomaa <otsaloma@iki.fi>
License: MIT
License-File: AUTHORS.md
License-File: COPYING
Requires-Python: >=3.9.0
Requires-Dist: attd>=0.3
Requires-Dist: numpy<3.0,>=2.0
Requires-Dist: pyarrow>=2.0
Requires-Dist: wcwidth>=0.1
